{
    "total": {
        "get_failing_tests_covered_classes": 1780,
        "get_code_snippet": 1853,
        "get_comments": 295,
        "get_failing_tests_covered_methods_for_class": 250
    },
    "failing": {
        "get_failing_tests_covered_classes": 0,
        "get_code_snippet": 725,
        "get_comments": 135,
        "get_failing_tests_covered_methods_for_class": 55
    },
    "steps": {
        "get_failing_tests_covered_classes": [
            1765,
            12,
            2,
            0,
            1,
            0,
            0,
            0,
            0,
            0,
            0
        ],
        "get_code_snippet": [
            0,
            1183,
            464,
            141,
            44,
            15,
            5,
            2,
            0,
            0,
            0
        ],
        "get_comments": [
            0,
            12,
            160,
            48,
            42,
            20,
            9,
            4,
            0,
            0,
            0
        ],
        "get_failing_tests_covered_methods_for_class": [
            0,
            237,
            7,
            3,
            1,
            2,
            0,
            0,
            0,
            0,
            0
        ]
    }
}